m/commands/ask/__init__.py
m/commands/ask/impl.py
m/commands/ask/markdown.py
m/commands/ask/types.py
m/commands/ask/utils.py
mm_chat-0.0.4.2.dist-info/METADATA
mm_chat-0.0.4.2.dist-info/WHEEL
mm_chat-0.0.4.2.dist-info/entry_points.txt
mm_chat-0.0.4.2.dist-info/RECORD
