Metadata-Version: 2.1
Name: mm-chat
Version: 0.0.4.2
Summary: Chat utilities for personal use
Requires-Python: >=3.12
Requires-Dist: hmr~=0.7.5
Requires-Dist: promplate[openai]<0.3.6.0,>=0.3.4.10
Requires-Dist: prompt-toolkit~=3.0.48
